EliasFanoDB.cpython-310-darwin.so
cpp_src/__init__.py
scfind/__init__.py
scfind/core_functions.py
scfind/core_methods.py
scfind-0.1.3.dist-info/licenses/LICENSE
scfind-0.1.3.dist-info/METADATA
scfind-0.1.3.dist-info/WHEEL
scfind-0.1.3.dist-info/top_level.txt
scfind-0.1.3.dist-info/RECORD
