Metadata-Version: 2.4
Name: scfind
Version: 0.1.3
Summary: scfind is a method for searching specific cell types from large single-cell datasets by a query of gene list. scfind can suggest subqueries score by TF-IDF method. scfind can perform hypergeometric test which allows the evaluation of marker genes specific to each cell type within a dataset.
Author: Nikolaos Patikasi, Shaokun An
Author-email: shan12@bwh.harvard.edu
Classifier: Development Status :: 3 - Alpha
Classifier: Intended Audience :: Developers
Classifier: Programming Language :: Python :: 3
Requires-Python: >=3.8
License-File: LICENSE
Requires-Dist: numpy>=1.24.4
Requires-Dist: scipy>=1.10.1
Requires-Dist: statsmodels>=0.14.0
Requires-Dist: pybind11>=2.11.1
Requires-Dist: pandas>=2.0.3
Requires-Dist: anndata>=0.9.2
Requires-Dist: setuptools>=68.0.0
Requires-Dist: tqdm>=4.66.1
Requires-Dist: python-Levenshtein>=0.23.0
Requires-Dist: h5py>=3.10.0
Requires-Dist: gensim>=4.3.2
Requires-Dist: fuzzywuzzy>=0.18.0
Requires-Dist: rapidfuzz>=3.5.2
Dynamic: author
Dynamic: author-email
Dynamic: classifier
Dynamic: description
Dynamic: description-content-type
Dynamic: license-file
Dynamic: requires-dist
Dynamic: requires-python
Dynamic: summary
